{
    "autocompleteArray": [
        "/j - joking",
        "/hj - half joking",
        "/srs - serious",
        "/s - sarcastic, sarcasm",
        "/lh - light hearted",
        "/nm - not mad or upset",
        "/gen or /g - geniune, geniunely",
        "/neg or /nc - negative connotation",
        "/pos or /pc - positive connotation",
        "/ij - inside joke",
        "/t - teasing",
        "/ly or /l - lyrics",
        "/p - platonic",
        "/r - romantic",
        "/nbh - nobody here, not directed at anyone here",
        "/m - metaphorically",
        "/li - literally",
        "/rh or /rt - rhetorical question",
        "/hyp - hyperbole",
        "/c - copypasta",
        "/sx or /x = sexual intent",
        "/nsx or /nx - non-sexual intent",
        "/th - threat",
        "/cb - clickbait",
        "/f - fake"
    ],


    "tones": {
        "/j": "`/j` = joking",
        "/hj": "`/hj` = half joking",
        "/srs": "`/srs` = serious",
        "/s": "`/s` = sarcasm, sarcastic",
        "/lh": "`/lh` = light hearted",
        "/nm": "`/nm` = not actually mad or upset",
        "/gen": "`/gen` or `/g` = geniune, geniunely",
        "/neg": "`/neg` or `/nc` = said with a negative connotation",
        "/pos": "`/pos` or `/pc` = said with a positive connotation",
        "/ij": "`/ij` = inside joke",
        "/t": "`/t` = teasing",
        "/ly": "`/ly` or `/l` = lyrics (from a song or theme tune or other piece of music)",
        "/p": "`/p` = platonic",
        "/r": "`/r` = romantic",
        "/nbh": "`/nbh` = nobody here, commonly used when venting (while being vague or keeping the person in question anonymous) to denote it isn't directed at anyone here",
        "/m": "`/m` = metaphorically",
        "/li": "`/li` = literally",
        "/rh": "`/rh` or `/rt` = rhetorical question",
        "/hyp": "`/hyp` = hyperbole (an exaggerated statement/claim, which is *not* meant to be taken literally)",
        "/c": "`/c` = a copypasta",
        "/sx": "`/sx` = said with a sexual intent",
        "/nsx": "`/nsx` = said with a **non-**sexual intent",
        "/th": "`/th` = a threat, or said threateningly",
        "/cb": "`/cb` = clickbait",
        "/f": "`/f` = fake"
    }
}
